mh_driver.py
mh_selenium/__init__.py
mh_selenium/utils.py
mh_selenium/pages/__init__.py
mh_selenium/pages/locators.py
mh_selenium/pages/page.py
dce_mh_selenium-0.2.0.dist-info/entry_points.txt
dce_mh_selenium-0.2.0.dist-info/DESCRIPTION.rst
dce_mh_selenium-0.2.0.dist-info/top_level.txt
dce_mh_selenium-0.2.0.dist-info/metadata.json
dce_mh_selenium-0.2.0.dist-info/WHEEL
dce_mh_selenium-0.2.0.dist-info/RECORD
dce_mh_selenium-0.2.0.dist-info/METADATA
