Metadata-Version: 2.0
Name: dce-mh-selenium
Version: 0.2.0
Summary: Selenium tasks and page objects for DCE Matterhorn
Home-page: https://github.com/harvard-dce/mh-selenium
Author: Jay Luker
Author-email: jay_luker@harvard.edu
License: Apache 2.0
Platform: UNKNOWN
Requires-Dist: selenium (==2.47.1)
Requires-Dist: click (==5.1)
Requires-Dist: fabric (==1.10.2)
Requires-Dist: pytimeparse (==1.1.5)
Requires-Dist: unipath (==1.1)
